README.rst
setup.py
timer.py
py_timer.egg-info/PKG-INFO
py_timer.egg-info/SOURCES.txt
py_timer.egg-info/dependency_links.txt
py_timer.egg-info/top_level.txt